pep610/__init__.py
pep610/_pep610.py
pep610/_types.py
pep610/py.typed
pep610-0.5.1.dist-info/METADATA
pep610-0.5.1.dist-info/WHEEL
pep610-0.5.1.dist-info/licenses/LICENSE
pep610-0.5.1.dist-info/RECORD
