Metadata-Version: 2.4
Name: pep610
Version: 0.5.1
Summary: PEP 610 Direct URL data parser
Project-URL: Documentation, https://pep610.readthedocs.io
Project-URL: Issues, https://github.com/edgarrmondragon/pep610/issues
Project-URL: Source, https://github.com/edgarrmondragon/pep610
Author-email: Edgar Ramírez Mondragón <edgarrmondragon@hey.com>
License-Expression: Apache-2.0
License-File: LICENSE
Keywords: packaging,pep,pep610
Classifier: Development Status :: 4 - Beta
Classifier: Programming Language :: Python
Classifier: Programming Language :: Python :: 3 :: Only
Classifier: Programming Language :: Python :: 3.8
Classifier: Programming Language :: Python :: 3.9
Classifier: Programming Language :: Python :: 3.10
Classifier: Programming Language :: Python :: 3.11
Classifier: Programming Language :: Python :: 3.12
Classifier: Programming Language :: Python :: 3.13
Classifier: Programming Language :: Python :: 3.14
Classifier: Programming Language :: Python :: 3.15
Classifier: Typing :: Typed
Requires-Python: >=3.8
